{"authority":"CANONICAL_RECORD","checkpoint_summary":"This normal full Atlas Sunset closes the chat while preserving the exact durable results and restart context. PR #245 merged the Atlas naming architecture refraction; PR #246 merged the deterministic generated refresh; and PR #247 merged Prime Integrity plus the future Gitea/Phoenix validation augmentation. Prime Ascendant is only the admitted-Quest continuity scope and remains ACTIVE — ARCHITECTURE REFINEMENT at PA-C01-COVENANT-REFINEMENT. Runtime is NOT STARTED, Gitea cutover is NOT AUTHORIZED, and legacy route retirement is NOT AUTHORIZED. The future validation route remains Gitea pull-request event to Prime Integrity Cognitive Shadow, immutable exact-base/exact-head carrier, bounded Kandra executor, conditional Windows executor, TenSoon verification, Phoenix draft/status publication, Athena audit, and Jayson-controlled permanence. No deployment, activation, settings, ruleset, cutover, runtime, or route-retirement action occurred.","concurrency":{"declared_source_fingerprint":"sha256:85374d0649abd657c920ea48847883f3aeb7430c6b746857acb4c3dcd665b03d","expected_main_sha":"8d4991b30e9809cee4a7cd3db9fdea3a9b3941cd","expected_parent_feather":"FTR-SCFUZB37GJBLW4SL2JSH32LQBP","expected_quest_revision":2},"emberline_id":"QEM-KYPFUDPMKFMO4UHFJGZMINITSO","evidence_pointers":[{"authority":"EVIDENCE_POINTER","digest":"sha256:cc99c59d155f5fb09057b9ecdfd81b203919fee417c95985b6b15c5ad60088d2","ref_id":"merged-pr-245-naming-architecture-refraction","uri":"quests/prime-ascendant.md"},{"authority":"EVIDENCE_POINTER","digest":"sha256:6cc3fedb2f33fa345d8b70d34f3b0251927c10d5c23a230e5bef56b655f0ee60","ref_id":"merged-pr-246-deterministic-generated-refresh","uri":"tools/prime_checks/targeted_validation.py"},{"authority":"EVIDENCE_POINTER","digest":"sha256:6cc3fedb2f33fa345d8b70d34f3b0251927c10d5c23a230e5bef56b655f0ee60","ref_id":"merged-pr-247-prime-integrity-gitea-phoenix-augmentation","uri":"tests/prime-program/test_targeted_validation.py"},{"authority":"EVIDENCE_POINTER","digest":"sha256:52e6b5037a17181737873aa03205e0e9a562651a7db6f364537ae8fa0e0a9b22","ref_id":"prime-ascendant-continuity-reconciliation","uri":"tests/prime-program/test_prime_ascendant_covenant.py"}],"feather_id":"FTR-DI2NRWYNLEBRSNY7TX6F4YIFMY","gate":"PA-C01-COVENANT-REFINEMENT","protected_data":{"classification":"INTERNAL_CLEAN","clean_summary":"Only sanitized doctrine, public repository identities, merged-PR evidence references, lifecycle state, unresolved work, and restart guidance are included. No credentials, tokens, keys, MFA or recovery codes, private network values, PHI, raw finance or account evidence, private exports, or unredacted logs are stored.","protected_pointers":[]},"quest_id":"prime-ascendant","quest_revision":2,"record_id":"QCP-MAEC477LNV2OWJJ5YSG65OVI4J","schema_id":"atlas.lifecycle.quest-checkpoint","schema_version":"1.0.0"}
